ordered_model/__init__.py
ordered_model/admin.py
ordered_model/apps.py
ordered_model/models.py
ordered_model/serializers.py
ordered_model/locale/de/LC_MESSAGES/django.mo
ordered_model/locale/de/LC_MESSAGES/django.po
ordered_model/locale/pl/LC_MESSAGES/django.mo
ordered_model/locale/pl/LC_MESSAGES/django.po
ordered_model/management/__init__.py
ordered_model/management/commands/__init__.py
ordered_model/management/commands/reorder_model.py
ordered_model/static/ordered_model/arrow-bottom.gif
ordered_model/static/ordered_model/arrow-down.gif
ordered_model/static/ordered_model/arrow-top.gif
ordered_model/static/ordered_model/arrow-up.gif
ordered_model/templates/ordered_model/admin/order_controls.html
django_ordered_model-3.7.3.dist-info/LICENSE
django_ordered_model-3.7.3.dist-info/METADATA
django_ordered_model-3.7.3.dist-info/WHEEL
django_ordered_model-3.7.3.dist-info/top_level.txt
django_ordered_model-3.7.3.dist-info/RECORD
