Metadata-Version: 2.1
Name: django-ordered-model
Version: 3.7.3
Summary: Allows Django models to be ordered and provides a simple admin interface for reordering them.
Home-page: http://github.com/django-ordered-model/django-ordered-model
Author: Ben Firshman
Author-email: ben@firshman.co.uk
Classifier: Development Status :: 5 - Production/Stable
Classifier: Framework :: Django
Classifier: Intended Audience :: Developers
Classifier: License :: OSI Approved :: BSD License
Classifier: Operating System :: OS Independent
Classifier: Programming Language :: Python
Classifier: Programming Language :: Python :: 3
Requires: Django
License-File: LICENSE
